<?xml version="1.0" encoding="UTF-8"?><testbuilder-item class="testcase" ident="tb_1452" number="57" name="TC-1076-1-10" library-name="FAClusterSlim.TestCase" start-time="15:23:21" start-date="2019-09-02"><metainfo></metainfo><parameter><argument name="CaptureResult" type="Main Library.Dictionary" inout="">{}</argument><argument name="ExclusionList" type="Main Library.List" inout="In">[]</argument><argument name="ExecutionParameters" type="Main Library.Dictionary" inout="In">{'SignalCapture': 'KeywordA'}</argument><argument name="Status" type="Main Library.Int" inout="">0</argument><argument name="StatusCode" type="Main Library.Int" inout="">0</argument><argument name="Clarification" type="Main Library.String" inout=""></argument></parameter><testbuilder-item class="phase" ident="tb_1453" number="57.1" name="Initialization" library-name="Test Builder.BaseBlock2" start-time="15:23:21" start-date="2019-09-02"><metainfo></metainfo><parameter></parameter><returnvalues></returnvalues><result><verdict>Executed</verdict><message></message></result></testbuilder-item><testbuilder-item class="phase" ident="tb_1454" number="57.2" name="ActionsAndEvaluation" library-name="Test Builder.EvaluationPhase" start-time="15:23:21" start-date="2019-09-02"><metainfo></metainfo><parameter></parameter><testbuilder-item class="phase" ident="tb_1455" number="57.2.1" name="TestCase" library-name="Test Builder.EvaluationPhase" start-time="15:23:21" start-date="2019-09-02"><metainfo></metainfo><parameter></parameter><testbuilder-item class="step" ident="tb_1456" number="57.2.1.1" name="GetAllProcesses" library-name="Universal Base Library.GetAllProcesses" start-time="15:23:21" start-date="2019-09-02"><metainfo></metainfo><parameter><argument name="PrintProcesses" type="Main Library.String" inout="In">No</argument><argument name="ProcessorActivity" type="Main Library.String" inout="In">No</argument></parameter><returnvalues><argument name="Status" type="Main Library.Int" inout="Out">0</argument><argument name="StatusCode" type="Main Library.Int" inout="Out">0</argument><argument name="StatusMessage" type="Main Library.String" inout="Out">Result is in output data objects 'ActiveProcessesList' or 'ActiveProcessesDetails'.</argument><argument name="ActiveProcessesDetails" type="Main Library.Dictionary" inout="Out">{'brkrprcs64.exe': [15880, 1445888], 'dwm.exe': [1800, 119128064, 3312, 36917248], 'unsecapp.exe': [5072, 2818048, 8284, 2830336], 'edpa.exe': [4824, 162893824], 'splwow64.exe': [9988, 9990144], 'SearchUI.exe': [7512, 119361536], 'KeyDownWrapper_ServerProxy.exe': [9276, 6463488], 'SgrmBroker.exe': [184, 4452352], 'Registry': [276, 28422144], 'webexmta.exe': [13096, 13295616], 'GGDS_ServerProxy.exe': [19708, 10158080], 'SettingSyncHost.exe': [5508, 1417216], 'ONENOTEM.EXE': [12712, 3166208], 'pacjsworker.exe': [5300, 5009408, 13512, 8818688], 'SecurityHealthService.exe': [10332, 10985472], 'kvoop.exe': [8620, 1495040, 8760, 1568768], 'ControlDesk.exe': [8312, 878841856], 'OUTLOOK.EXE': [4956, 129978368], 'msiexec.exe': [17192, 14970880], 'svchost.exe': [1476, 1503232, 1532, 22577152, 1624, 13709312, 1668, 7659520, 1712, 10776576, 1860, 5636096, 1956, 2883584, 1964, 112943104, 1988, 3215360, 1996, 7262208, 200, 5439488, 1056, 5685248, 1492, 3002368, 2076, 12525568, 2096, 7032832, 2104, 4960256, 2172, 1986560, 2188, 4325376, 2264, 16547840, 2332, 6598656, 2580, 9773056, 2652, 14532608, 2740, 5464064, 2748, 6963200, 2836, 6344704, 2948, 3579904, 2956, 4751360, 2968, 6709248, 3108, 4210688, 3188, 5472256, 3236, 33615872, 3252, 4767744, 3316, 5070848, 3440, 5558272, 3576, 3497984, 3708, 5292032, 3952, 2719744, 3948, 245506048, 3964, 6217728, 4068, 4276224, 4072, 5799936, 3392, 10252288, 4112, 11677696, 4212, 3338240, 4220, 4096000, 4280, 4710400, 4816, 25141248, 4848, 6541312, 4856, 48041984, 4872, 2068480, 4880, 1990656, 4904, 1802240, 4912, 2625536, 4924, 17125376, 4940, 2752512, 5336, 22712320, 5860, 1974272, 6008, 1806336, 4980, 4710400, 6960, 4055040, 7772, 3862528, 5372, 7692288, 9356, 4042752, 9404, 8269824, 9768, 17408000, 2576, 5206016, 5872, 12079104, 10028, 17727488, 4104, 17063936, 2664, 5677056, 8644, 13533184, 10616, 5636096, 7736, 3538944, 5392, 4210688, 8440, 2154496, 11108, 5832704, 18808, 7340032, 17248, 6586368], 'smartscreen.exe': [11172, 22970368], 'TabTip.exe': [11528, 9805824], 'WindowsInternal.ComposableShell.Experiences.TextInput.InputApp.exe': [696, 25075712], 'System': [4, 28672], 'sepWscSvc64.exe': [5356, 3813376], 'dllhost.exe': [10812, 5660672, 14372, 5132288], 'DSEESPortServer.exe': [12816, 27164672], 'LogonUI.exe': [15812, 53006336], 'CodeMeter.exe': [4764, 17055744], 'explorer.exe': [9696, 148697088], 'smss.exe': [856, 700416], 'RuntimeBroker.exe': [9872, 17494016, 7832, 24047616, 11884, 6156288, 1792, 19783680, 11408, 20189184, 11036, 25731072], 'System Idle Process': [0, 8192], 'cmd.exe': [16996, 1204224], 'CiscoCollabHostCef.exe': [12516, 9908224, 15692, 7217152], 'EXCEL.EXE': [5904, 139431936], 'rdpclip.exe': [15232, 12517376], 'SecurityHealthSystray.exe': [7660, 5140480], 'lsass.exe': [1324, 22233088], 'services.exe': [1292, 14082048], 'ptoneclk.exe': [12804, 11968512], 'RtkNGUI64.exe': [11668, 9842688], 'ccSvcHst.exe': [4948, 207712256, 10296, 4591616], 'armsvc.exe': [4736, 1748992], 'CATSysDemon.exe': [4744, 1482752], 'YourPhone.exe': [11604, 10362880], 'taskhostw.exe': [9232, 15171584], 'ctfmon.exe': [19032, 21880832], 'WINWORD.EXE': [17788, 150315008], 'RAVBg64.exe': [4172, 9936896, 4192, 10223616, 11996, 10686464, 11420, 4124672], 'NwmSvc.exe': [4864, 11030528], 'LockApp.exe': [7920, 37294080], 'RtkAudioService64.exe': [3468, 2805760], 'chrome.exe': [6048, 57470976, 15616, 5844992, 11368, 5398528, 15992, 32112640, 16064, 17014784, 12244, 9121792, 14812, 18259968, 17092, 11026432, 13984, 9129984], 'CcmExec.exe': [8744, 68370432], 'ehost.exe': [4784, 8142848], 'nvvsvc.exe': [2344, 5607424, 3164, 7593984, 12872, 15593472], 'python.exe': [3912, 11739136, 5828, 16248832], 'AutomationDesk.exe': [13380, 3249229824L], 'DSXILMAPortServer.exe': [3488, 314503168], 'VisFastStart.exe': [4604, 12472320], 'SCNotification.exe': [11032, 29069312], 'ptSrv.exe': [13172, 2502656], 'policyHost.exe': [9900, 16220160], 'CiscoCollabHost.exe': [11268, 107339776, 13188, 42438656, 10692, 6569984], 'NwmCli.exe': [12016, 6037504], 'wdp.exe': [4896, 2666496], 'sihost.exe': [10508, 23162880], 'spoolsv.exe': [4492, 18399232], 'wininit.exe': [1172, 2072576], 'DSPSVCN.exe': [4776, 2842624], 'winlogon.exe': [1284, 6066176, 13108, 8974336], 'Memory Compression': [4020, 0], 'PLinMng.exe': [4832, 3751936], 'SearchIndexer.exe': [10248, 71237632], 'csrss.exe': [1084, 2441216, 1184, 3575808, 5368, 4849664], 'dSPACE.PmServiceHost.exe': [4800, 30507008], 'WmiPrvSE.exe': [6092, 56221696, 8016, 12046336, 9912, 5058560, 4144, 11833344, 12528, 8548352, 7800, 43724800], 'fontdrvhost.exe': [1496, 5623808, 1548, 11071488, 18704, 6955008], 'PTIM.exe': [5544, 1769472], 'In-Sight.exe': [9804, 32026624], 'ShellExperienceHost.exe': [10328, 70590464], 'nvwmi64.exe': [3816, 3604480, 4204, 14962688], 'DsDevAccSvc.exe': [4792, 2646016], '@Ford.DesktopApplication.exe': [8716, 32673792], 'BLHealthMon.exe': [4808, 18518016], 'In-Sight Explorer.exe': [10220, 500617216], 'TSVNCache.exe': [8040, 23425024], 'WakeUpAgt.exe': [4932, 6344704], 'Chaoss.exe': [9064, 42725376], 'conhost.exe': [11652, 8933376, 9260, 8937472, 11328, 6447104, 16432, 8904704, 8892, 11681792, 20308, 13815808, 19996, 13807616], 'Microsoft.Photos.exe': [1980, 50675712], 'CUI.exe': [1748, 16785408]}</argument><argument name="ActiveProcessesList" type="Main Library.List" inout="Out">['@Ford.DesktopApplication.exe', 'armsvc.exe', 'AutomationDesk.exe', 'BLHealthMon.exe', 'brkrprcs64.exe', 'CATSysDemon.exe', 'CcmExec.exe', 'ccSvcHst.exe', 'ccSvcHst.exe', 'Chaoss.exe', 'chrome.exe', 'chrome.exe', 'chrome.exe', 'chrome.exe', 'chrome.exe', 'chrome.exe', 'chrome.exe', 'chrome.exe', 'chrome.exe', 'CiscoCollabHost.exe', 'CiscoCollabHost.exe', 'CiscoCollabHost.exe', 'CiscoCollabHostCef.exe', 'CiscoCollabHostCef.exe', 'cmd.exe', 'CodeMeter.exe', 'conhost.exe', 'conhost.exe', 'conhost.exe', 'conhost.exe', 'conhost.exe', 'conhost.exe', 'conhost.exe', 'ControlDesk.exe', 'csrss.exe', 'csrss.exe', 'csrss.exe', 'ctfmon.exe', 'CUI.exe', 'dllhost.exe', 'dllhost.exe', 'DsDevAccSvc.exe', 'DSEESPortServer.exe', 'dSPACE.PmServiceHost.exe', 'DSPSVCN.exe', 'DSXILMAPortServer.exe', 'dwm.exe', 'dwm.exe', 'edpa.exe', 'ehost.exe', 'EXCEL.EXE', 'explorer.exe', 'fontdrvhost.exe', 'fontdrvhost.exe', 'fontdrvhost.exe', 'GGDS_ServerProxy.exe', 'In-Sight Explorer.exe', 'In-Sight.exe', 'KeyDownWrapper_ServerProxy.exe', 'kvoop.exe', 'kvoop.exe', 'LockApp.exe', 'LogonUI.exe', 'lsass.exe', 'Memory Compression', 'Microsoft.Photos.exe', 'msiexec.exe', 'nvvsvc.exe', 'nvvsvc.exe', 'nvvsvc.exe', 'nvwmi64.exe', 'nvwmi64.exe', 'NwmCli.exe', 'NwmSvc.exe', 'ONENOTEM.EXE', 'OUTLOOK.EXE', 'pacjsworker.exe', 'pacjsworker.exe', 'PLinMng.exe', 'policyHost.exe', 'PTIM.exe', 'ptoneclk.exe', 'ptSrv.exe', 'python.exe', 'python.exe', 'RAVBg64.exe', 'RAVBg64.exe', 'RAVBg64.exe', 'RAVBg64.exe', 'rdpclip.exe', 'Registry', 'RtkAudioService64.exe', 'RtkNGUI64.exe', 'RuntimeBroker.exe', 'RuntimeBroker.exe', 'RuntimeBroker.exe', 'RuntimeBroker.exe', 'RuntimeBroker.exe', 'RuntimeBroker.exe', 'SCNotification.exe', 'SearchIndexer.exe', 'SearchUI.exe', 'SecurityHealthService.exe', 'SecurityHealthSystray.exe', 'sepWscSvc64.exe', 'services.exe', 'SettingSyncHost.exe', 'SgrmBroker.exe', 'ShellExperienceHost.exe', 'sihost.exe', 'smartscreen.exe', 'smss.exe', 'splwow64.exe', 'spoolsv.exe', 'svchost.exe', 'svchost.exe', 'svchost.exe', 'svchost.exe', 'svchost.exe', 'svchost.exe', 'svchost.exe', 'svchost.exe', 'svchost.exe', 'svchost.exe', 'svchost.exe', 'svchost.exe', 'svchost.exe', 'svchost.exe', 'svchost.exe', 'svchost.exe', 'svchost.exe', 'svchost.exe', 'svchost.exe', 'svchost.exe', 'svchost.exe', 'svchost.exe', 'svchost.exe', 'svchost.exe', 'svchost.exe', 'svchost.exe', 'svchost.exe', 'svchost.exe', 'svchost.exe', 'svchost.exe', 'svchost.exe', 'svchost.exe', 'svchost.exe', 'svchost.exe', 'svchost.exe', 'svchost.exe', 'svchost.exe', 'svchost.exe', 'svchost.exe', 'svchost.exe', 'svchost.exe', 'svchost.exe', 'svchost.exe', 'svchost.exe', 'svchost.exe', 'svchost.exe', 'svchost.exe', 'svchost.exe', 'svchost.exe', 'svchost.exe', 'svchost.exe', 'svchost.exe', 'svchost.exe', 'svchost.exe', 'svchost.exe', 'svchost.exe', 'svchost.exe', 'svchost.exe', 'svchost.exe', 'svchost.exe', 'svchost.exe', 'svchost.exe', 'svchost.exe', 'svchost.exe', 'svchost.exe', 'svchost.exe', 'svchost.exe', 'svchost.exe', 'svchost.exe', 'svchost.exe', 'svchost.exe', 'svchost.exe', 'svchost.exe', 'svchost.exe', 'svchost.exe', 'svchost.exe', 'svchost.exe', 'svchost.exe', 'System', 'System Idle Process', 'TabTip.exe', 'taskhostw.exe', 'TSVNCache.exe', 'unsecapp.exe', 'unsecapp.exe', 'VisFastStart.exe', 'WakeUpAgt.exe', 'wdp.exe', 'webexmta.exe', 'WindowsInternal.ComposableShell.Experiences.TextInput.InputApp.exe', 'wininit.exe', 'winlogon.exe', 'winlogon.exe', 'WINWORD.EXE', 'WmiPrvSE.exe', 'WmiPrvSE.exe', 'WmiPrvSE.exe', 'WmiPrvSE.exe', 'WmiPrvSE.exe', 'WmiPrvSE.exe', 'YourPhone.exe']</argument></returnvalues><result><verdict>Executed</verdict><message></message></result></testbuilder-item><testbuilder-item class="step" ident="tb_1457" number="57.2.1.2" name="GetADOperationMode" library-name="Universal Base Library.GetADOperationMode" start-time="15:23:22" start-date="2019-09-02"><metainfo></metainfo><parameter></parameter><returnvalues><argument name="OperationModeConst" type="Main Library.String" inout="Out"></argument><argument name="OperationModeValue" type="Main Library.Int" inout="Out">-1</argument><argument name="Status" type="Main Library.Int" inout="Out">0</argument><argument name="StatusCode" type="Main Library.Int" inout="Out">0</argument><argument name="StatusMessage" type="Main Library.String" inout="Out">Ok!</argument></returnvalues><result><verdict>Executed</verdict><message></message></result></testbuilder-item><testbuilder-item class="step" ident="tb_1458" number="57.2.1.3" name="StartReadingCognexTelnet" library-name="FAClusterSlim.StartReadingCognexTelnet" start-time="15:23:22" start-date="2019-09-02"><metainfo></metainfo><parameter></parameter><returnvalues></returnvalues><result><verdict>Executed</verdict><message></message></result></testbuilder-item><testbuilder-item class="step" ident="tb_1459" number="57.2.1.4" name="SetAwdHiLamp_D_RqDsply" library-name="FAClusterSlim.SetAwdHiLamp_D_RqDsply" start-time="15:23:28" start-date="2019-09-02"><metainfo></metainfo><parameter><argument name="Parameter" type="Main Library.String" inout="In">Off</argument></parameter><returnvalues></returnvalues><result><verdict>Executed</verdict><message></message></result></testbuilder-item><testbuilder-item class="step" ident="tb_1460" number="57.2.1.5" name="SetDiagnosticSessionControl" library-name="FAClusterSlim.SetDiagnosticSessionControl" start-time="15:23:29" start-date="2019-09-02"><metainfo></metainfo><parameter><argument name="ECUName" type="Main Library.String" inout="In">IPC</argument><argument name="Session" type="Main Library.String" inout="In">ExtendedDiagnosticSession</argument></parameter><returnvalues><argument name="Clarification" type="Main Library.String" inout="Out"></argument><argument name="FrostbyteError" type="Main Library.Int" inout="Out">0</argument><argument name="ErrorMessage" type="Main Library.String" inout="Out"></argument></returnvalues><result><verdict>Executed</verdict><message></message></result></testbuilder-item><testbuilder-item class="step" ident="tb_1461" number="57.2.1.6" name="SetInputOutputSessionControl" library-name="FAClusterSlim.SetInputOutputSessionControl" start-time="15:23:30" start-date="2019-09-02"><metainfo></metainfo><parameter><argument name="ECUName" type="Main Library.String" inout="In">IPC</argument><argument name="DID" type="Main Library.String" inout="In">61CE</argument><argument name="Byte" type="Main Library.Int" inout="In">3</argument><argument name="Bit" type="Main Library.Int" inout="In">6</argument><argument name="ControlMaskLength" type="Main Library.Int" inout="In">8</argument><argument name="Status" type="Main Library.String" inout="In">On</argument></parameter><testbuilder-item class="step" ident="tb_1462" number="57.2.1.6.1" name="SetChallengeBytesUnlock" library-name="FAClusterSlim.SetChallengeBytesUnlock" start-time="15:23:30" start-date="2019-09-02"><metainfo></metainfo><parameter></parameter><returnvalues><argument name="Clarification" type="Main Library.String" inout="Out"></argument></returnvalues><result><verdict>Executed</verdict><message></message></result></testbuilder-item><testbuilder-item class="check" ident="tb_1463" number="57.2.1.6.2" name="TestStepEvaluation" library-name="Test Builder.Check" start-time="15:23:35" start-date="2019-09-02"><metainfo></metainfo><parameter></parameter><returnvalues></returnvalues><result><verdict>Passed</verdict><message></message></result></testbuilder-item><returnvalues></returnvalues><result><verdict>Passed</verdict><message></message></result></testbuilder-item><testbuilder-item class="step" ident="tb_1464" number="57.2.1.7" name="WaitXY" library-name="FAClusterSlim.WaitXY" start-time="15:23:35" start-date="2019-09-02"><metainfo></metainfo><parameter><argument name="WaitTime" type="Main Library.Float" inout="In">5</argument><argument name="Dimension" type="Main Library.String" inout="In">seconds</argument></parameter><returnvalues><argument name="Clarification" type="Main Library.String" inout="Out"></argument></returnvalues><result><verdict>Executed</verdict><message></message></result></testbuilder-item><testbuilder-item class="step" ident="tb_1465" number="57.2.1.8" name="StopReadingCognexTelnet" library-name="FAClusterSlim.StopReadingCognexTelnet" start-time="15:23:41" start-date="2019-09-02"><metainfo></metainfo><parameter></parameter><returnvalues></returnvalues><result><verdict>Executed</verdict><message></message></result></testbuilder-item><testbuilder-item class="step" ident="tb_1466" number="57.2.1.9" name="CheckTelltale" library-name="FAClusterSlim.CheckTelltale" start-time="15:23:42" start-date="2019-09-02"><metainfo></metainfo><parameter><argument name="Id" type="Main Library.String" inout="In">R740</argument><argument name="Expected" type="Main Library.String" inout="In">AnyOn</argument></parameter><testbuilder-item class="step" ident="tb_1467" number="57.2.1.9.1" name="CheckSignalPatternOn" library-name="Ford Test Framework.Frame" start-time="15:23:43" start-date="2019-09-02"><metainfo></metainfo><parameter><argument name="CaptureResult" type="Main Library.Dictionary" inout="In">{'R740': [0, 0, 0, 0, 0, 0, 0, 0, 0, 0, 0, 0, 0, 0, 0, 0, 0, 0, 0, 0, 0, 0, 0, 0, 0, 0, 0, 0, 0, 0, 0, 0, 0, 0, 0, 0, 0, 0, 0, 0, 0, 0, 0, 0, 0, 0, 0, 0, 0, 0, 0, 0, 0, 0, 0, 0, 0, 0, 0, 0, 0, 0, 0, 0, 0, 0, 0, 0, 0, 0, 0, 0, 0, 0, 0, 0, 0, 0, 0, 0, 0, 0, 0, 0, 0, 0, 0, 0, 0, 0, 0, 0, 0, 0, 0, 0, 0, 0, 0, 0, 0, 0, 0, 0, 0, 0, 0, 0, 0, 0, 0, 0, 0, 0, 0, 0, 0, 0, 0, 0, 0, 0, 0, 0, 0, 0, 0, 0, 0, 0, 0, 0, 0, 0, 0, 0, 0, 0, 0, 0, 0, 0, 0, 0, 0, 0, 0, 0, 0, 0, 0, 0, 0, 0, 0, 0, 0, 0, 0, 0, 0, 0, 0, 0, 0, 0, 0, 0, 0, 0, 0, 0, 0, 0, 0, 0, 0, 0, 0, 0, 0, 0, 0, 0, 0, 0, 0, 0, 0, 0, 0, 0, 0, 0, 0, 0, 0, 0, 0, 0, 0, 0, 0, 0, 0, 0, 0, 0, 0, 0, 0, 0, 0, 0, 0, 0, 0, 0, 0, 0, 0, 0, 0, 0, 0, 0, 0, 0, 0, 0, 0, 0, 0, 0, 0, 0, 0, 0, 0, 0, 0, 0, 0, 0, 0, 0, 0, 0, 0, 0, 0, 0, 0, 0, 0, 0, 0, 0, 0, 0, 0, 0, 0, 0, 0, 1, 1, 1, 1, 1, 1, 1, 1, 1, 1, 1, 1, 1, 1, 1, 1, 1, 1, 1, 1, 1, 1, 1, 1, 1, 1, 1, 1, 1, 1, 1, 1, 1, 1, 1, 1, 1, 1, 1, 1, 1, 1, 1, 1, 1, 1, 1, 1, 1, 1, 1, 1, 1, 1, 1, 1, 1, 1, 1, 1, 1, 1, 1, 1, 1, 1, 1, 1, 1, 1, 1, 1, 1, 1, 1, 1, 1, 1, 1, 1, 1, 1, 1, 1, 1, 1, 1, 1, 1, 1, 1, 1, 1, 1, 1, 1, 1, 1, 1, 1, 0, 0, 0, 0, 0, 0, 0, 0, 0, 0, 0, 0, 0, 0, 0, 0, 0, 0, 0, 0, 0, 0, 0, 0, 0, 0, 0, 0, 0, 0, 0, 0, 0, 0, 0, 0, 0, 0, 0, 0, 0, 0, 0, 0, 0, 0, 0, 0, 0, 0, 0, 0, 0, 0, 0, 0, 0, 0, 0, 0, 0, 0, 0, 0, 0, 0, 0, 0, 0, 0, 0, 0, 0, 0, 0, 0, 0, 0, 0, 0], 'xAxis': [0.127, 0.131, 0.134, 0.137, 0.14, 0.143, 0.146, 0.149, 0.152, 0.155, 0.158, 0.161, 0.164, 0.167, 0.17, 0.173, 0.176, 0.179, 0.182, 0.185, 0.188, 0.191, 0.194, 0.197, 0.2, 0.203, 0.206, 0.21, 0.212, 0.215, 0.218, 0.221, 0.225, 0.676, 0.682, 0.686, 0.69, 0.696, 0.701, 0.706, 0.71, 0.713, 0.716, 0.719, 0.723, 1.129, 1.133, 1.137, 1.141, 1.145, 1.149, 1.153, 1.157, 1.161, 1.165, 1.169, 1.172, 1.176, 1.179, 1.183, 1.187, 1.191, 1.195, 1.199, 1.201, 1.205, 1.209, 1.211, 1.216, 1.22, 1.224, 1.629, 1.634, 1.638, 1.643, 1.648, 1.653, 1.657, 1.661, 1.666, 1.669, 1.672, 1.675, 1.764, 2.138, 2.142, 2.146, 2.15, 2.154, 2.157, 2.162, 2.166, 2.171, 2.174, 2.179, 2.182, 2.185, 2.189, 2.193, 2.197, 2.201, 2.205, 2.209, 2.213, 2.216, 2.221, 2.225, 2.631, 2.639, 2.644, 2.65, 2.655, 2.659, 2.664, 2.669, 2.674, 2.678, 2.683, 2.688, 2.693, 2.698, 2.705, 2.71, 2.714, 2.718, 2.723, 3.131, 3.135, 3.139, 3.142, 3.145, 3.148, 3.151, 3.154, 3.157, 3.16, 3.163, 3.166, 3.169, 3.172, 3.175, 3.178, 3.181, 3.184, 3.187, 3.19, 3.193, 3.196, 3.199, 3.202, 3.205, 3.209, 3.212, 3.215, 3.218, 3.221, 3.224, 3.638, 3.642, 3.646, 3.649, 3.653, 3.656, 3.659, 3.664, 3.667, 3.672, 3.675, 3.679, 3.683, 3.687, 3.692, 3.696, 3.7, 3.704, 3.708, 3.712, 3.716, 3.719, 3.724, 4.128, 4.132, 4.135, 4.139, 4.143, 4.147, 4.151, 4.155, 4.158, 4.163, 4.166, 4.171, 4.175, 4.178, 4.182, 4.186, 4.189, 4.193, 4.196, 4.2, 4.204, 4.207, 4.211, 4.215, 4.219, 4.223, 4.623, 4.627, 4.63, 4.633, 4.636, 4.639, 4.642, 4.645, 4.648, 4.651, 4.654, 4.657, 4.66, 4.663, 4.666, 4.669, 4.672, 4.675, 4.678, 4.681, 4.684, 4.688, 4.691, 4.695, 4.699, 4.702, 4.705, 4.708, 4.711, 4.714, 4.718, 4.721, 4.724, 5.187, 5.196, 5.2, 5.204, 5.207, 5.21, 5.214, 5.217, 5.22, 5.224, 5.666, 5.67, 5.674, 5.678, 5.682, 5.685, 5.69, 5.694, 5.698, 5.702, 5.705, 5.71, 5.714, 5.718, 5.722, 5.726, 6.319, 6.671, 6.676, 6.68, 6.684, 6.688, 6.69, 6.695, 6.699, 6.703, 6.707, 6.711, 6.715, 6.718, 6.722, 6.726, 7.207, 7.211, 7.215, 7.219, 7.223, 7.226, 7.67, 7.674, 7.677, 7.681, 7.684, 7.687, 7.691, 7.694, 7.697, 7.701, 7.705, 7.708, 7.712, 7.715, 7.718, 7.722, 7.726, 8.186, 8.19, 8.194, 8.198, 8.201, 8.204, 8.207, 8.211, 8.215, 8.219, 8.224, 8.709, 8.713, 8.716, 8.72, 8.723, 9.222, 9.226, 9.666, 9.671, 9.675, 9.679, 9.683, 9.687, 9.691, 9.695, 9.699, 9.703, 9.706, 9.833, 10.165, 10.169, 10.173, 10.176, 10.18, 10.184, 10.188, 10.191, 10.196, 10.199, 10.203, 10.207, 10.211, 10.215, 10.219, 10.223, 10.226, 10.676, 10.68, 10.684, 10.688, 10.692, 10.695, 10.7, 10.703, 10.707, 10.711, 10.715, 10.719, 10.723, 10.727, 11.128, 11.132, 11.136, 11.14, 11.143, 11.147, 11.151, 11.155, 11.158, 11.162, 11.165, 11.169, 11.174, 11.178, 11.182, 11.186, 11.19, 11.194, 11.198, 11.202, 11.206, 11.21, 11.214, 11.218, 11.222, 11.226, 11.634, 11.638, 11.642, 11.646, 11.65, 11.654, 11.658, 11.662, 11.665, 11.668, 11.672, 11.676, 11.679, 11.683, 11.686, 11.69, 11.694, 11.698, 11.702, 11.705, 11.708, 11.711, 11.715, 11.719, 11.722, 11.725, 12.659, 12.688, 12.693, 12.697, 12.701, 12.705, 12.709, 12.713, 12.717, 12.721, 12.724, 13.171, 13.175, 13.178, 13.182, 13.185, 13.189, 13.193, 13.196, 13.199, 13.203, 13.206, 13.209, 13.213, 13.216, 13.219, 13.224, 13.63]}</argument><argument name="SignalDescriptionText" type="Main Library.String" inout="In">On</argument><argument name="SignalDescription" type="Main Library.Variant" inout="">[{_AD_.Id:["Const(1)"]}]</argument></parameter><returnvalues><argument name="SignalDescription" type="Main Library.Variant" inout="">[{_AD_.Id:["Const(1)"]}]</argument><argument name="CheckResult" type="Main Library.String" inout="Out">Failed</argument></returnvalues><result><verdict>Executed</verdict><message></message></result></testbuilder-item><testbuilder-item class="step" ident="tb_1468" number="57.2.1.9.2" name="CheckSignalPatternOffToOn" library-name="Ford Test Framework.Frame" start-time="15:23:43" start-date="2019-09-02"><metainfo></metainfo><parameter><argument name="CaptureResult" type="Main Library.Dictionary" inout="In">{'R740': [0, 0, 0, 0, 0, 0, 0, 0, 0, 0, 0, 0, 0, 0, 0, 0, 0, 0, 0, 0, 0, 0, 0, 0, 0, 0, 0, 0, 0, 0, 0, 0, 0, 0, 0, 0, 0, 0, 0, 0, 0, 0, 0, 0, 0, 0, 0, 0, 0, 0, 0, 0, 0, 0, 0, 0, 0, 0, 0, 0, 0, 0, 0, 0, 0, 0, 0, 0, 0, 0, 0, 0, 0, 0, 0, 0, 0, 0, 0, 0, 0, 0, 0, 0, 0, 0, 0, 0, 0, 0, 0, 0, 0, 0, 0, 0, 0, 0, 0, 0, 0, 0, 0, 0, 0, 0, 0, 0, 0, 0, 0, 0, 0, 0, 0, 0, 0, 0, 0, 0, 0, 0, 0, 0, 0, 0, 0, 0, 0, 0, 0, 0, 0, 0, 0, 0, 0, 0, 0, 0, 0, 0, 0, 0, 0, 0, 0, 0, 0, 0, 0, 0, 0, 0, 0, 0, 0, 0, 0, 0, 0, 0, 0, 0, 0, 0, 0, 0, 0, 0, 0, 0, 0, 0, 0, 0, 0, 0, 0, 0, 0, 0, 0, 0, 0, 0, 0, 0, 0, 0, 0, 0, 0, 0, 0, 0, 0, 0, 0, 0, 0, 0, 0, 0, 0, 0, 0, 0, 0, 0, 0, 0, 0, 0, 0, 0, 0, 0, 0, 0, 0, 0, 0, 0, 0, 0, 0, 0, 0, 0, 0, 0, 0, 0, 0, 0, 0, 0, 0, 0, 0, 0, 0, 0, 0, 0, 0, 0, 0, 0, 0, 0, 0, 0, 0, 0, 0, 0, 0, 0, 0, 0, 0, 0, 0, 1, 1, 1, 1, 1, 1, 1, 1, 1, 1, 1, 1, 1, 1, 1, 1, 1, 1, 1, 1, 1, 1, 1, 1, 1, 1, 1, 1, 1, 1, 1, 1, 1, 1, 1, 1, 1, 1, 1, 1, 1, 1, 1, 1, 1, 1, 1, 1, 1, 1, 1, 1, 1, 1, 1, 1, 1, 1, 1, 1, 1, 1, 1, 1, 1, 1, 1, 1, 1, 1, 1, 1, 1, 1, 1, 1, 1, 1, 1, 1, 1, 1, 1, 1, 1, 1, 1, 1, 1, 1, 1, 1, 1, 1, 1, 1, 1, 1, 1, 1, 0, 0, 0, 0, 0, 0, 0, 0, 0, 0, 0, 0, 0, 0, 0, 0, 0, 0, 0, 0, 0, 0, 0, 0, 0, 0, 0, 0, 0, 0, 0, 0, 0, 0, 0, 0, 0, 0, 0, 0, 0, 0, 0, 0, 0, 0, 0, 0, 0, 0, 0, 0, 0, 0, 0, 0, 0, 0, 0, 0, 0, 0, 0, 0, 0, 0, 0, 0, 0, 0, 0, 0, 0, 0, 0, 0, 0, 0, 0, 0], 'xAxis': [0.127, 0.131, 0.134, 0.137, 0.14, 0.143, 0.146, 0.149, 0.152, 0.155, 0.158, 0.161, 0.164, 0.167, 0.17, 0.173, 0.176, 0.179, 0.182, 0.185, 0.188, 0.191, 0.194, 0.197, 0.2, 0.203, 0.206, 0.21, 0.212, 0.215, 0.218, 0.221, 0.225, 0.676, 0.682, 0.686, 0.69, 0.696, 0.701, 0.706, 0.71, 0.713, 0.716, 0.719, 0.723, 1.129, 1.133, 1.137, 1.141, 1.145, 1.149, 1.153, 1.157, 1.161, 1.165, 1.169, 1.172, 1.176, 1.179, 1.183, 1.187, 1.191, 1.195, 1.199, 1.201, 1.205, 1.209, 1.211, 1.216, 1.22, 1.224, 1.629, 1.634, 1.638, 1.643, 1.648, 1.653, 1.657, 1.661, 1.666, 1.669, 1.672, 1.675, 1.764, 2.138, 2.142, 2.146, 2.15, 2.154, 2.157, 2.162, 2.166, 2.171, 2.174, 2.179, 2.182, 2.185, 2.189, 2.193, 2.197, 2.201, 2.205, 2.209, 2.213, 2.216, 2.221, 2.225, 2.631, 2.639, 2.644, 2.65, 2.655, 2.659, 2.664, 2.669, 2.674, 2.678, 2.683, 2.688, 2.693, 2.698, 2.705, 2.71, 2.714, 2.718, 2.723, 3.131, 3.135, 3.139, 3.142, 3.145, 3.148, 3.151, 3.154, 3.157, 3.16, 3.163, 3.166, 3.169, 3.172, 3.175, 3.178, 3.181, 3.184, 3.187, 3.19, 3.193, 3.196, 3.199, 3.202, 3.205, 3.209, 3.212, 3.215, 3.218, 3.221, 3.224, 3.638, 3.642, 3.646, 3.649, 3.653, 3.656, 3.659, 3.664, 3.667, 3.672, 3.675, 3.679, 3.683, 3.687, 3.692, 3.696, 3.7, 3.704, 3.708, 3.712, 3.716, 3.719, 3.724, 4.128, 4.132, 4.135, 4.139, 4.143, 4.147, 4.151, 4.155, 4.158, 4.163, 4.166, 4.171, 4.175, 4.178, 4.182, 4.186, 4.189, 4.193, 4.196, 4.2, 4.204, 4.207, 4.211, 4.215, 4.219, 4.223, 4.623, 4.627, 4.63, 4.633, 4.636, 4.639, 4.642, 4.645, 4.648, 4.651, 4.654, 4.657, 4.66, 4.663, 4.666, 4.669, 4.672, 4.675, 4.678, 4.681, 4.684, 4.688, 4.691, 4.695, 4.699, 4.702, 4.705, 4.708, 4.711, 4.714, 4.718, 4.721, 4.724, 5.187, 5.196, 5.2, 5.204, 5.207, 5.21, 5.214, 5.217, 5.22, 5.224, 5.666, 5.67, 5.674, 5.678, 5.682, 5.685, 5.69, 5.694, 5.698, 5.702, 5.705, 5.71, 5.714, 5.718, 5.722, 5.726, 6.319, 6.671, 6.676, 6.68, 6.684, 6.688, 6.69, 6.695, 6.699, 6.703, 6.707, 6.711, 6.715, 6.718, 6.722, 6.726, 7.207, 7.211, 7.215, 7.219, 7.223, 7.226, 7.67, 7.674, 7.677, 7.681, 7.684, 7.687, 7.691, 7.694, 7.697, 7.701, 7.705, 7.708, 7.712, 7.715, 7.718, 7.722, 7.726, 8.186, 8.19, 8.194, 8.198, 8.201, 8.204, 8.207, 8.211, 8.215, 8.219, 8.224, 8.709, 8.713, 8.716, 8.72, 8.723, 9.222, 9.226, 9.666, 9.671, 9.675, 9.679, 9.683, 9.687, 9.691, 9.695, 9.699, 9.703, 9.706, 9.833, 10.165, 10.169, 10.173, 10.176, 10.18, 10.184, 10.188, 10.191, 10.196, 10.199, 10.203, 10.207, 10.211, 10.215, 10.219, 10.223, 10.226, 10.676, 10.68, 10.684, 10.688, 10.692, 10.695, 10.7, 10.703, 10.707, 10.711, 10.715, 10.719, 10.723, 10.727, 11.128, 11.132, 11.136, 11.14, 11.143, 11.147, 11.151, 11.155, 11.158, 11.162, 11.165, 11.169, 11.174, 11.178, 11.182, 11.186, 11.19, 11.194, 11.198, 11.202, 11.206, 11.21, 11.214, 11.218, 11.222, 11.226, 11.634, 11.638, 11.642, 11.646, 11.65, 11.654, 11.658, 11.662, 11.665, 11.668, 11.672, 11.676, 11.679, 11.683, 11.686, 11.69, 11.694, 11.698, 11.702, 11.705, 11.708, 11.711, 11.715, 11.719, 11.722, 11.725, 12.659, 12.688, 12.693, 12.697, 12.701, 12.705, 12.709, 12.713, 12.717, 12.721, 12.724, 13.171, 13.175, 13.178, 13.182, 13.185, 13.189, 13.193, 13.196, 13.199, 13.203, 13.206, 13.209, 13.213, 13.216, 13.219, 13.224, 13.63]}</argument><argument name="SignalDescriptionText" type="Main Library.String" inout="In">OffToOn</argument><argument name="SignalDescription" type="Main Library.Variant" inout="">[{_AD_.Id:["Const(0)","Const(1)"]}]</argument></parameter><returnvalues><argument name="SignalDescription" type="Main Library.Variant" inout="">[{_AD_.Id:["Const(0)","Const(1)"]}]</argument><argument name="CheckResult" type="Main Library.String" inout="Out">Failed</argument></returnvalues><result><verdict>Executed</verdict><message></message></result></testbuilder-item><testbuilder-item class="step" ident="tb_1469" number="57.2.1.9.3" name="CheckSignalPatternPulseOn" library-name="Ford Test Framework.Frame" start-time="15:23:43" start-date="2019-09-02"><metainfo></metainfo><parameter><argument name="CaptureResult" type="Main Library.Dictionary" inout="In">{'R740': [0, 0, 0, 0, 0, 0, 0, 0, 0, 0, 0, 0, 0, 0, 0, 0, 0, 0, 0, 0, 0, 0, 0, 0, 0, 0, 0, 0, 0, 0, 0, 0, 0, 0, 0, 0, 0, 0, 0, 0, 0, 0, 0, 0, 0, 0, 0, 0, 0, 0, 0, 0, 0, 0, 0, 0, 0, 0, 0, 0, 0, 0, 0, 0, 0, 0, 0, 0, 0, 0, 0, 0, 0, 0, 0, 0, 0, 0, 0, 0, 0, 0, 0, 0, 0, 0, 0, 0, 0, 0, 0, 0, 0, 0, 0, 0, 0, 0, 0, 0, 0, 0, 0, 0, 0, 0, 0, 0, 0, 0, 0, 0, 0, 0, 0, 0, 0, 0, 0, 0, 0, 0, 0, 0, 0, 0, 0, 0, 0, 0, 0, 0, 0, 0, 0, 0, 0, 0, 0, 0, 0, 0, 0, 0, 0, 0, 0, 0, 0, 0, 0, 0, 0, 0, 0, 0, 0, 0, 0, 0, 0, 0, 0, 0, 0, 0, 0, 0, 0, 0, 0, 0, 0, 0, 0, 0, 0, 0, 0, 0, 0, 0, 0, 0, 0, 0, 0, 0, 0, 0, 0, 0, 0, 0, 0, 0, 0, 0, 0, 0, 0, 0, 0, 0, 0, 0, 0, 0, 0, 0, 0, 0, 0, 0, 0, 0, 0, 0, 0, 0, 0, 0, 0, 0, 0, 0, 0, 0, 0, 0, 0, 0, 0, 0, 0, 0, 0, 0, 0, 0, 0, 0, 0, 0, 0, 0, 0, 0, 0, 0, 0, 0, 0, 0, 0, 0, 0, 0, 0, 0, 0, 0, 0, 0, 0, 1, 1, 1, 1, 1, 1, 1, 1, 1, 1, 1, 1, 1, 1, 1, 1, 1, 1, 1, 1, 1, 1, 1, 1, 1, 1, 1, 1, 1, 1, 1, 1, 1, 1, 1, 1, 1, 1, 1, 1, 1, 1, 1, 1, 1, 1, 1, 1, 1, 1, 1, 1, 1, 1, 1, 1, 1, 1, 1, 1, 1, 1, 1, 1, 1, 1, 1, 1, 1, 1, 1, 1, 1, 1, 1, 1, 1, 1, 1, 1, 1, 1, 1, 1, 1, 1, 1, 1, 1, 1, 1, 1, 1, 1, 1, 1, 1, 1, 1, 1, 0, 0, 0, 0, 0, 0, 0, 0, 0, 0, 0, 0, 0, 0, 0, 0, 0, 0, 0, 0, 0, 0, 0, 0, 0, 0, 0, 0, 0, 0, 0, 0, 0, 0, 0, 0, 0, 0, 0, 0, 0, 0, 0, 0, 0, 0, 0, 0, 0, 0, 0, 0, 0, 0, 0, 0, 0, 0, 0, 0, 0, 0, 0, 0, 0, 0, 0, 0, 0, 0, 0, 0, 0, 0, 0, 0, 0, 0, 0, 0], 'xAxis': [0.127, 0.131, 0.134, 0.137, 0.14, 0.143, 0.146, 0.149, 0.152, 0.155, 0.158, 0.161, 0.164, 0.167, 0.17, 0.173, 0.176, 0.179, 0.182, 0.185, 0.188, 0.191, 0.194, 0.197, 0.2, 0.203, 0.206, 0.21, 0.212, 0.215, 0.218, 0.221, 0.225, 0.676, 0.682, 0.686, 0.69, 0.696, 0.701, 0.706, 0.71, 0.713, 0.716, 0.719, 0.723, 1.129, 1.133, 1.137, 1.141, 1.145, 1.149, 1.153, 1.157, 1.161, 1.165, 1.169, 1.172, 1.176, 1.179, 1.183, 1.187, 1.191, 1.195, 1.199, 1.201, 1.205, 1.209, 1.211, 1.216, 1.22, 1.224, 1.629, 1.634, 1.638, 1.643, 1.648, 1.653, 1.657, 1.661, 1.666, 1.669, 1.672, 1.675, 1.764, 2.138, 2.142, 2.146, 2.15, 2.154, 2.157, 2.162, 2.166, 2.171, 2.174, 2.179, 2.182, 2.185, 2.189, 2.193, 2.197, 2.201, 2.205, 2.209, 2.213, 2.216, 2.221, 2.225, 2.631, 2.639, 2.644, 2.65, 2.655, 2.659, 2.664, 2.669, 2.674, 2.678, 2.683, 2.688, 2.693, 2.698, 2.705, 2.71, 2.714, 2.718, 2.723, 3.131, 3.135, 3.139, 3.142, 3.145, 3.148, 3.151, 3.154, 3.157, 3.16, 3.163, 3.166, 3.169, 3.172, 3.175, 3.178, 3.181, 3.184, 3.187, 3.19, 3.193, 3.196, 3.199, 3.202, 3.205, 3.209, 3.212, 3.215, 3.218, 3.221, 3.224, 3.638, 3.642, 3.646, 3.649, 3.653, 3.656, 3.659, 3.664, 3.667, 3.672, 3.675, 3.679, 3.683, 3.687, 3.692, 3.696, 3.7, 3.704, 3.708, 3.712, 3.716, 3.719, 3.724, 4.128, 4.132, 4.135, 4.139, 4.143, 4.147, 4.151, 4.155, 4.158, 4.163, 4.166, 4.171, 4.175, 4.178, 4.182, 4.186, 4.189, 4.193, 4.196, 4.2, 4.204, 4.207, 4.211, 4.215, 4.219, 4.223, 4.623, 4.627, 4.63, 4.633, 4.636, 4.639, 4.642, 4.645, 4.648, 4.651, 4.654, 4.657, 4.66, 4.663, 4.666, 4.669, 4.672, 4.675, 4.678, 4.681, 4.684, 4.688, 4.691, 4.695, 4.699, 4.702, 4.705, 4.708, 4.711, 4.714, 4.718, 4.721, 4.724, 5.187, 5.196, 5.2, 5.204, 5.207, 5.21, 5.214, 5.217, 5.22, 5.224, 5.666, 5.67, 5.674, 5.678, 5.682, 5.685, 5.69, 5.694, 5.698, 5.702, 5.705, 5.71, 5.714, 5.718, 5.722, 5.726, 6.319, 6.671, 6.676, 6.68, 6.684, 6.688, 6.69, 6.695, 6.699, 6.703, 6.707, 6.711, 6.715, 6.718, 6.722, 6.726, 7.207, 7.211, 7.215, 7.219, 7.223, 7.226, 7.67, 7.674, 7.677, 7.681, 7.684, 7.687, 7.691, 7.694, 7.697, 7.701, 7.705, 7.708, 7.712, 7.715, 7.718, 7.722, 7.726, 8.186, 8.19, 8.194, 8.198, 8.201, 8.204, 8.207, 8.211, 8.215, 8.219, 8.224, 8.709, 8.713, 8.716, 8.72, 8.723, 9.222, 9.226, 9.666, 9.671, 9.675, 9.679, 9.683, 9.687, 9.691, 9.695, 9.699, 9.703, 9.706, 9.833, 10.165, 10.169, 10.173, 10.176, 10.18, 10.184, 10.188, 10.191, 10.196, 10.199, 10.203, 10.207, 10.211, 10.215, 10.219, 10.223, 10.226, 10.676, 10.68, 10.684, 10.688, 10.692, 10.695, 10.7, 10.703, 10.707, 10.711, 10.715, 10.719, 10.723, 10.727, 11.128, 11.132, 11.136, 11.14, 11.143, 11.147, 11.151, 11.155, 11.158, 11.162, 11.165, 11.169, 11.174, 11.178, 11.182, 11.186, 11.19, 11.194, 11.198, 11.202, 11.206, 11.21, 11.214, 11.218, 11.222, 11.226, 11.634, 11.638, 11.642, 11.646, 11.65, 11.654, 11.658, 11.662, 11.665, 11.668, 11.672, 11.676, 11.679, 11.683, 11.686, 11.69, 11.694, 11.698, 11.702, 11.705, 11.708, 11.711, 11.715, 11.719, 11.722, 11.725, 12.659, 12.688, 12.693, 12.697, 12.701, 12.705, 12.709, 12.713, 12.717, 12.721, 12.724, 13.171, 13.175, 13.178, 13.182, 13.185, 13.189, 13.193, 13.196, 13.199, 13.203, 13.206, 13.209, 13.213, 13.216, 13.219, 13.224, 13.63]}</argument><argument name="SignalDescriptionText" type="Main Library.String" inout="In">PulseOn</argument><argument name="SignalDescription" type="Main Library.Variant" inout="">[{_AD_.Id: ["Const(0)","Pulse(1)", "Const(0)"]}]</argument></parameter><returnvalues><argument name="SignalDescription" type="Main Library.Variant" inout="">[{_AD_.Id: ["Const(0)","Pulse(1)", "Const(0)"]}]</argument><argument name="CheckResult" type="Main Library.String" inout="Out">Passed</argument></returnvalues><result><verdict>Executed</verdict><message></message></result></testbuilder-item><testbuilder-item class="addverdict" ident="tb_1470" number="57.2.1.9.4" name="AddVerdict1" library-name="Test Builder.AddVerdict" start-time="15:23:44" start-date="2019-09-02"><metainfo></metainfo><parameter></parameter><returnvalues></returnvalues><result><verdict>Passed</verdict><message></message></result></testbuilder-item><returnvalues><argument name="Clarification" type="Main Library.String" inout="Out">Reference to an requirement, Intention of check block</argument><argument name="LogOutputFilename" type="Main Library.String" inout="Out">C:\HIL\Transient\CognexLogs\R740HighFixed1_20190902_152322.csv</argument></returnvalues><result><verdict>Passed</verdict><message></message></result></testbuilder-item><testbuilder-item class="step" ident="tb_1471" number="57.2.1.10" name="StopReadingCognexTelnet" library-name="FAClusterSlim.StopReadingCognexTelnet" start-time="15:23:47" start-date="2019-09-02"><metainfo></metainfo><parameter></parameter><returnvalues></returnvalues><result><verdict>Executed</verdict><message></message></result></testbuilder-item><testbuilder-item class="step" ident="tb_1472" number="57.2.1.11" name="SetAwdHiLamp_D_RqDsply" library-name="FAClusterSlim.SetAwdHiLamp_D_RqDsply" start-time="15:23:47" start-date="2019-09-02"><metainfo></metainfo><parameter><argument name="Parameter" type="Main Library.String" inout="In">Off</argument></parameter><returnvalues></returnvalues><result><verdict>Executed</verdict><message></message></result></testbuilder-item><testbuilder-item class="step" ident="tb_1473" number="57.2.1.12" name="SetDiagnosticSessionControl" library-name="FAClusterSlim.SetDiagnosticSessionControl" start-time="15:23:48" start-date="2019-09-02"><metainfo></metainfo><parameter><argument name="ECUName" type="Main Library.String" inout="In">IPC</argument><argument name="Session" type="Main Library.String" inout="In">DefaultSession</argument></parameter><returnvalues><argument name="Clarification" type="Main Library.String" inout="Out"></argument><argument name="FrostbyteError" type="Main Library.Int" inout="Out">0</argument><argument name="ErrorMessage" type="Main Library.String" inout="Out"></argument></returnvalues><result><verdict>Executed</verdict><message></message></result></testbuilder-item><testbuilder-item class="step" ident="tb_1474" number="57.2.1.13" name="SetIgnition" library-name="FAClusterSlim.SetIgnition" start-time="15:23:49" start-date="2019-09-02"><metainfo></metainfo><parameter><argument name="Parameter" type="Main Library.String" inout="">Run</argument></parameter><returnvalues><argument name="Parameter" type="Main Library.String" inout="">Run</argument></returnvalues><result><verdict>Executed</verdict><message></message></result></testbuilder-item><testbuilder-item class="step" ident="tb_1475" number="57.2.1.14" name="WaitXY" library-name="FAClusterSlim.WaitXY" start-time="15:23:50" start-date="2019-09-02"><metainfo></metainfo><parameter><argument name="WaitTime" type="Main Library.Float" inout="In">5</argument><argument name="Dimension" type="Main Library.String" inout="In">seconds</argument></parameter><returnvalues><argument name="Clarification" type="Main Library.String" inout="Out"></argument></returnvalues><result><verdict>Executed</verdict><message></message></result></testbuilder-item><returnvalues></returnvalues><result><verdict>Passed</verdict><message></message></result></testbuilder-item><returnvalues></returnvalues><result><verdict>Passed</verdict><message></message></result></testbuilder-item><testbuilder-item class="phase" ident="tb_1476" number="57.3" name="Cleanup" library-name="Test Builder.BaseBlock2" start-time="15:23:59" start-date="2019-09-02"><metainfo></metainfo><parameter></parameter><returnvalues></returnvalues><result><verdict>Executed</verdict><message></message></result></testbuilder-item><returnvalues><argument name="CaptureResult" type="Main Library.Dictionary" inout="">{}</argument><argument name="SignalCaptureList" type="Main Library.List" inout="Out">[]</argument><argument name="Status" type="Main Library.Int" inout="">0</argument><argument name="StatusCode" type="Main Library.Int" inout="">0</argument><argument name="Clarification" type="Main Library.String" inout=""></argument></returnvalues><result><verdict>Passed</verdict><message></message></result></testbuilder-item>